missmate/__init__.py
missmate/utils.py
missmate/visualisation_axes.py
missmate/visualisation_text.py
missmate-0.1.0.dist-info/LICENSE
missmate-0.1.0.dist-info/METADATA
missmate-0.1.0.dist-info/WHEEL
missmate-0.1.0.dist-info/RECORD
